eigen_client/__init__.py
eigen_client/client.py
eigen_client/data_types.py
eigen_client/index.py
eigen_client/response.py
eigen_client/supported_models.py
eigen_client/utils.py
eigen_client-1.0.4.dist-info/METADATA
eigen_client-1.0.4.dist-info/WHEEL
eigen_client-1.0.4.dist-info/top_level.txt
eigen_client-1.0.4.dist-info/RECORD
