Metadata-Version: 2.4
Name: eigen-client
Version: 1.0.4
Summary: EigenDB's Official Python API
Author-email: Ryan Awad <ryanawad@yahoo.com>
Project-URL: Homepage, https://github.com/Eigen-DB/eigen-db/tree/main/libs/eigen-py
Project-URL: Issues, https://github.com/Eigen-DB/eigen-db/issues
Classifier: Programming Language :: Python :: 3
Classifier: License :: OSI Approved :: MIT License
Classifier: Operating System :: OS Independent
Requires-Python: >=3.8
Requires-Dist: requests==2.29.0
Requires-Dist: pytest==8.4.1
Requires-Dist: tiktoken==0.11.0
Requires-Dist: ollama==0.5.3
Requires-Dist: openai==1.101.0
